date2name/__init__.py
date2name-2024.4.26.1.dist-info/LICENSE.txt
date2name-2024.4.26.1.dist-info/METADATA
date2name-2024.4.26.1.dist-info/WHEEL
date2name-2024.4.26.1.dist-info/entry_points.txt
date2name-2024.4.26.1.dist-info/RECORD
