Metadata-Version: 2.1
Name: date2name
Version: 2024.4.26.1
Summary: Handling time-stamps and date-stamps in file names
License: GPL v3
Author: Karl Voit
Author-email: tools@Karl-Voit.at
Requires-Python: >=3.9,<4.0
Classifier: License :: Other/Proprietary License
Classifier: Programming Language :: Python :: 3
Classifier: Programming Language :: Python :: 3.9
Classifier: Programming Language :: Python :: 3.10
Classifier: Programming Language :: Python :: 3.11
